[{"name":"name","species":"Cat","weight":2.0,"chipId":2374984,"height":2.0,"width":2.0,"length":2.0,"birthDate":{"year":2022,"month":5,"day":9},"owner":{"name":"name","email":"email","age":20,"password":"password","userType":"Vet","id":"3278697"},"id":"37987"},{"name":"name2","species":"Cat","weight":2.0,"chipId":2374984,"height":2.0,"width":2.0,"length":2.0,"birthDate":{"year":2022,"month":5,"day":9},"owner":{"name":"name","email":"email","age":20,"password":"password","userType":"Vet","id":"3278697"},"id":"37987"},{"name":"name","species":"Cat","weight":2.0,"chipId":2374984,"height":2.0,"width":2.0,"length":2.0,"birthDate":{"year":2022,"month":5,"day":9},"owner":{"name":"name","email":"email","age":20,"password":"password","userType":"Vet","id":"3278697"},"id":"37987"},{"name":"name2","species":"Cat","weight":2.0,"chipId":2374984,"height":2.0,"width":2.0,"length":2.0,"birthDate":{"year":2022,"month":5,"day":9},"owner":{"name":"name","email":"email","age":20,"password":"password","userType":"Vet","id":"3278697"},"id":"37987"}]